Workbook

Sheet LAI
Q1: jdurand - 2022-05-16 14:34
A4: Rapport statistique sur la Loi sur l’accès à l’information
A6: Nom de l’institution: | K6: =IF(D6="", "Vous devez entrer un nom d'institution", "") -> Vous devez entrer un nom d'institution
A8: Période d'établissement de rapport : | F8: 45748 | H8: au | I8: 46112
A10: Section 1 – Demandes en vertu de la Loi sur l’accès à l’information (LAI)
A12: 1.1 Nombre de demandes
H13: Nombre de demandes
A14: Reçues pendant la période d'établissement de rapport | H14: 0
A15: En suspens à la fin de la période d'établissement de rapport précédente | H15: =G16+G17 -> 0
A16: • En suspens à la fin de la période d'établissement de rapport précédente | G16: 0
A17: • En suspens pour plus d'une période d'établissement de rapport | G17: 0
A18: Total | H18: =H14+H15 -> 0
A19: Fermées pendant la période d'établissement de rapport | H19: 0
A20: Reportées à la prochaine période d'établissement de rapport | H20: =SUM(G21:G22) -> 0
A21: • Reportées à la prochaine période d'établissement de rapport dans les délais prévus par la LAI | G21: 0 | K21: =IF(H20<>(H18-H19),"""Reportées à la prochaine période d'établissement de rapport"" doit être égal au ""Total"" moins ""Fermées pendant la période d'établissement de rapport""","")
A22: • Reportées à la prochaine période d'établissement de rapport au-delà des délais prévus par la LAI | G22: 0
A24: 1.2 Source des demandes
A26: Source | G26: Nombre de demandes
A27: Médias | G27: 0
A28: Secteur universitaire | G28: 0
A29: Secteur commercial (secteur privé) | G29: 0
A30: Organisation | G30: 0
A31: Public | G31: 0
A32: Refus de s'identifier | G32: 0
A33: Total | G33: =SUM(G27:J32) -> 0
A35: 1.3 Mode des demandes
A37: Mode | G37: Nombre des demandes
A38: En ligne | G38: 0
A39: Courriel | G39: 0
A40: Poste | G40: 0
A41: En personne | G41: 0
A42: Téléphone | G42: 0
A43: Télécopieur | G43: 0
A44: Total | G44: =SUM(G38:J43) -> 0
A46: Section 2 – Demandes informelles
A48: 2.1 Nombre de demandes informelles
H49: Nombre de demandes
A50: Reçues pendant la période d'établissement de rapport | H50: 0
A51: En suspens à la fin de la période d'établissement de rapport précédente | H51: =SUM(G52:G53) -> 0
A52: • En suspens à la fin de la période d'établissement de rapport précédente | G52: 0
A53: • En suspens pour plus d'une période d'établissement de rapport | G53: 0
A54: Total | H54: =SUM(H50:J51) -> 0
A55: Fermées pendant la période d'établissement de rapport | H55: 0
A56: Reportées à la prochaine période d'établissement de rapport | H56: =H54-H55 -> 0
A58: 2.2 Délai de traitement pour les demandes informelles
A60: Délai de traitement
A61: 0 à 15 jours | B61: 16 à 30 jours | C61: 31 à 60 jours | D61: 61 à 120 jours | E61: 121 à 180 jours | F61: 181 à 365 jours | G61: Plus de 365 jours | H61: Total
A62: 0 | B62: 0 | C62: 0 | D62: 0 | E62: 0 | F62: 0 | G62: 0 | H62: =SUM(A62:G62) -> 0
A64: 2.3 Pages communiquées et recommuniquées informellement
A66: Moins de 500 pages recommuniquées | C66: De 500 à 10 000 pages recommuniquées | E66: Plus de 10 000 pages recommuniquées
A67: Nombre de demandes | B67: Nombre de pages | C67: Nombre de demandes | D67: Nombre de pages | E67: Nombre de demandes | F67: Nombre de pages
A68: 0 | B68: 0 | C68: 0 | D68: 0 | E68: 0 | F68: 0
A70: Section 3 – Demandes à la Commissaire à l'information pour ne pas donner suite à la demande
H72: Nombre de demandes
A73: En suspens depuis la période d’établissement de rapports précédente | H73: 0
A74: Envoyées pendant la période d’établissement de rapports | H74: 0
A75: Total | H75: =SUM(H73:K74) -> 0
A76: Approuvées par la Commissaire à l’information pendant la période d’établissement de rapports | H76: 0
A77: Refusées par la Commissaire à l’information au cours de la période d’établissement de rapports | H77: 0
A78: Retirées pendant la période d'établissement de rapports | H78: 0
A79: Reportées à la prochaine période d’établissement de rapports | H79: 0
A81: Section 4 – Demandes fermées pendant la période d'établissement de rapports
A83: 4.1 Disposition et délai de traitement
A85: Disposition des demandes | E85: Délai de traitement
E86: 0 à 15 jours | F86: 16 à 30 jours | G86: 31 à 60 jours | H86: 61 à 120 jours | I86: 121 à 180 jours | J86: 181 à 365 jours | K86: Plus de 365 jours | L86: Total | N86: Nombre de demandes | O86: Pages traitées
A87: Communication totale | E87: 0 | F87: 0 | G87: 0 | H87: 0 | I87: 0 | J87: 0 | K87: 0 | L87: =SUM(E87:K87) -> 0 | N87: =SUM(#REF!,I167,#REF!) -> #REF! | O87: =SUM(I149,J167,#REF!) -> #REF!
A88: Communication partielle | E88: 0 | F88: 0 | G88: 0 | H88: 0 | I88: 0 | J88: 0 | K88: 0 | L88: =SUM(E88:K88) -> 0 | N88: =SUM(#REF!,I168,#REF!) -> #REF! | O88: =SUM(I150,J168,#REF!) -> #REF!
A89: Exception totale | E89: 0 | F89: 0 | G89: 0 | H89: 0 | I89: 0 | J89: 0 | K89: 0 | L89: =SUM(E89:K89) -> 0 | N89: =SUM(#REF!,I169,#REF!) -> #REF! | O89: =SUM(I151,J169,#REF!) -> #REF!
A90: Exclusion totale | E90: 0 | F90: 0 | G90: 0 | H90: 0 | I90: 0 | J90: 0 | K90: 0 | L90: =SUM(E90:K90) -> 0 | N90: =SUM(#REF!,I170,#REF!) -> #REF! | O90: =SUM(I152,J170,#REF!) -> #REF!
A91: Aucun document n’existe | E91: 0 | F91: 0 | G91: 0 | H91: 0 | I91: 0 | J91: 0 | K91: 0 | L91: =SUM(E91:K91) -> 0
A92: Demande transférée | E92: 0 | F92: 0 | G92: 0 | H92: 0 | I92: 0 | J92: 0 | K92: 0 | L92: =SUM(E92:K92) -> 0
A93: Demande abandonnée | E93: 0 | F93: 0 | G93: 0 | H93: 0 | I93: 0 | J93: 0 | K93: 0 | L93: =SUM(E93:K93) -> 0 | N93: =SUM(#REF!,I171,#REF!) -> #REF! | O93: =SUM(I153,J171,#REF!) -> #REF!
A94: Ni confirmée ni infirmée | E94: 0 | F94: 0 | G94: 0 | H94: 0 | I94: 0 | J94: 0 | K94: 0 | L94: =SUM(E94:K94) -> 0 | N94: =SUM(#REF!,I172,#REF!) -> #REF! | O94: =SUM(I154,J172,#REF!) -> #REF!
A95: Refus d'agir avec l'approbation de la Commissaire à l'information | E95: 0 | F95: 0 | G95: 0 | H95: 0 | I95: 0 | J95: 0 | K95: 0 | L95: =SUM(E95:K95) -> 0 | N95: =SUM(#REF!,I173,#REF!) -> #REF! | O95: =SUM(I155,J173,#REF!) -> #REF!
A96: Total | E96: =SUM(E87:E95) -> 0 | F96: =SUM(F87:F95) -> 0 | G96: =SUM(G87:G95) -> 0 | H96: =SUM(H87:H95) -> 0 | I96: =SUM(I87:I95) -> 0 | J96: =SUM(J87:J95) -> 0 | K96: =SUM(K87:K95) -> 0 | L96: =SUM(L87:L95) -> 0 | M96: =IF(L96<>H19,"""Total"" doit être égal au ""Fermées pendant la période d'établissement de rapport""","")
A98: 4.2 Exceptions
A100: Article | C100: Nombre de demandes | D100: Article | F100: Nombre de demandes | G100: Article | I100: Nombre de demandes | J100: Article | L100: Nombre de demandes
A101: 13(1)a) | C101: 0 | D101: 16(2) | F101: 0 | G101: 18a) | I101: 0 | J101: 20.1 | L101: 0
A102: 13(1)b) | C102: 0 | D102: 16(2)a) | F102: 0 | G102: 18b) | I102: 0 | J102: 20.2 | L102: 0
A103: 13(1)c) | C103: 0 | D103: 16(2)b) | F103: 0 | G103: 18c) | I103: 0 | J103: 20.4 | L103: 0
A104: 13(1)d) | C104: 0 | D104: 16(2)c) | F104: 0 | G104: 18d) | I104: 0 | J104: 21(1)a) | L104: 0
A105: 13(1)e) | C105: 0 | D105: 16(3) | F105: 0 | G105: 18.1(1)a) | I105: 0 | J105: 21(1)b) | L105: 0
A106: 14 | C106: 0 | D106: 16.1(1)a) | F106: 0 | G106: 18.1(1)b) | I106: 0 | J106: 21(1)c) | L106: 0
A107: 14a) | C107: 0 | D107: 16.1(1)b) | F107: 0 | G107: 18.1(1)c) | I107: 0 | J107: 21(1)d) | L107: 0
A108: 14b) | C108: 0 | D108: 16.1(1)c) | F108: 0 | G108: 18.1(1)d) | I108: 0 | J108: 22 | L108: 0
A109: 15(1) | C109: 0 | D109: 16.1(1)d) | F109: 0 | G109: 19(1) | I109: 0 | J109: 22.1(1) | L109: 0
A110: 15(1) - A.I.* | C110: 0 | D110: 16.2(1) | F110: 0 | G110: 20(1)a) | I110: 0 | J110: 23 | L110: 0
A111: 15(1) - Déf.* | C111: 0 | D111: 16.3 | F111: 0 | G111: 20(1)b) | I111: 0 | J111: 23.1 | L111: 0
A112: 15(1) - A.S.* | C112: 0 | D112: 16.4(1)a) | F112: 0 | G112: 20(1)b.1) | I112: 0 | J112: 24(1) | L112: 0
A113: 16(1)a)(i) | C113: 0 | D113: 16.4(1)b) | F113: 0 | G113: 20(1)c) | I113: 0 | J113: 26 | L113: 0
A114: 16(1)a)(ii) | C114: 0 | D114: 16.5 | F114: 0 | G114: 20(1)d) | I114: 0
A115: 16(1)a)(iii) | C115: 0 | D115: 16.6 | F115: 0
A116: 16(1)b) | C116: 0 | D116: 17 | F116: 0
A117: 16(1)c) | C117: 0
A118: 16(1)d) | C118: 0 | E118: *A.I. : Affaires internationales Déf. : Défense du Canada A.S. : Activités subversives
A120: 4.3 Exclusions
A122: Article | C122: Nombre de demandes | E122: Article | G122: Nombre de demandes | I122: Article | K122: Nombre de demandes
A123: 68a) | C123: 0 | E123: 69(1) | G123: 0 | I123: 69(1)g) re a) | K123: 0
A124: 68b) | C124: 0 | E124: 69(1)a) | G124: 0 | I124: 69(1)g) re b) | K124: 0
A125: 68c) | C125: 0 | E125: 69(1)b) | G125: 0 | I125: 69(1)g) re c) | K125: 0
...

Sheet LPRP
AA1: JDURAND - 2022-05-13 12:05
A4: Rapport statistique sur la Loi sur la protection des renseignements personnels
E6: Nom de l’institution: | O6: =IF(H6="", "Vous devez entrer un nom d'institution", "") -> Vous devez entrer un nom d'institution
E8: Période d'établissement de rapport : | H8: 45748 | K8: au | L8: 46112
A10: Section 1 – Demandes en vertu de la Loi sur la protection des renseignements personnels (LPRP)
A12: 1.1 Nombre de demandes reçues
H14: Nombre de demandes
A15: Reçues pendant la période d'établissement de rapport | H15: 0
A16: En suspens à la fin de la période d'établissement de rapport précédente | H16: =SUM(G17:G18) -> 0
A17: • En suspens à la fin de la période d'établissement de rapport précédente | G17: 0
A18: • En suspens pour plus d'une période d'établissement de rapport | G18: 0
A19: Total | H19: =SUM(H15:J16) -> 0
A20: Fermées pendant la période d'établissement de rapport | H20: 0
A21: Reportées à la prochaine période d'établissement de rapport | H21: =SUM(G22:G23) -> 0
A22: • Reportées à la prochaine période d'établissement de rapport dans les délais prévus par la LPRP | G22: 0 | K22: =IF(H21<>(H19-H20),"""Reportées à la prochaine période d'établissement de rapport"" doit être égal au ""Total"" moins ""Fermées pendant la période d'établissement de rapport""","")
A23: • Reportées à la prochaine période d'établissement de rapport au-delà des délais prévus par la LPRP | G23: 0
A25: 1.2 Mode des demandes
A27: Mode | G27: Nombre des demandes
A28: En ligne | G28: 0
A29: Courriel | G29: 0
A30: Poste | G30: 0
A31: En personne | G31: 0
A32: Téléphone | G32: 0
A33: Télécopieur | G33: 0
A34: Total | G34: =SUM(G28:J33) -> 0
A36: Section 2 – Demandes informelles
A38: 2.1 Nombre de demandes informelles
H39: Nombre de demandes
A40: Reçues pendant la période d'établissement de rapport | H40: 0
A41: En suspens à la fin de la période d'établissement de rapport précédente | H41: =SUM(G42:G43) -> 0
A42: • En suspens à la fin de la période d'établissement de rapport précédente | G42: 0
A43: • En suspens pour plus d'une période d'établissement de rapport | G43: 0
A44: Total | H44: =SUM(H40:J41) -> 0
A45: Fermées pendant la période d'établissement de rapport | H45: 0
A46: Reportées à la prochaine période d'établissement de rapport | H46: =H44-H45 -> 0
A48: 2.2 Délai de traitement pour les demandes informelles
A50: Délai de traitement
A51: 0 à 15 jours | B51: 16 à 30 jours | C51: 31 à 60 jours | D51: 61 à 120 jours | E51: 121 à 180 jours | F51: 181 à 365 jours | G51: Plus de 365 jours | H51: Total
A52: 0 | B52: 0 | C52: 0 | D52: 0 | E52: 0 | F52: 0 | G52: 0 | H52: =SUM(A52:G52) -> 0
A54: 2.3 Pages communiquées informellement
A56: Moins de 500 pages communiquées | C56: De 500 à 10 000 pages communiquées | E56: Plus de 10 000 pages communiquées
A57: Nombre de demandes | B57: Pages communiquées | C57: Nombre de demandes | D57: Pages communiquées | E57: Nombre de demandes | F57: Pages communiquées
A58: 0 | B58: 0 | C58: 0 | D58: 0 | E58: 0 | F58: 0
A61: Section 3 – Demandes fermées pendant la période d'établissement de rapport
A63: 3.1 Disposition et délai de traitement
A65: Disposition des demandes | D65: Délai de traitement
D66: 0 à 15 jours | E66: 16 à 30 jours | F66: 31 à 60 jours | G66: 61 à 120 jours | H66: 121 à 180 jours | I66: 181 à 365 jours | J66: Plus de 365 jours | K66: Total
A67: Communication totale | D67: 0 | E67: 0 | F67: 0 | G67: 0 | H67: 0 | I67: 0 | J67: 0 | K67: =SUM(D67:J67) -> 0 | AA67: =SUM(W117,S134,#REF!) -> #REF!
A68: Communication partielle | D68: 0 | E68: 0 | F68: 0 | G68: 0 | H68: 0 | I68: 0 | J68: 0 | K68: =SUM(D68:J68) -> 0 | AA68: =SUM(W118,S135,#REF!) -> #REF!
A69: Exception totale | D69: 0 | E69: 0 | F69: 0 | G69: 0 | H69: 0 | I69: 0 | J69: 0 | K69: =SUM(D69:J69) -> 0 | AA69: =SUM(W119,S136,#REF!) -> #REF!
A70: Exclusion totale | D70: 0 | E70: 0 | F70: 0 | G70: 0 | H70: 0 | I70: 0 | J70: 0 | K70: =SUM(D70:J70) -> 0 | AA70: =SUM(W120,S137,#REF!) -> #REF!
A71: Aucun document n’existe | D71: 0 | E71: 0 | F71: 0 | G71: 0 | H71: 0 | I71: 0 | J71: 0 | K71: =SUM(D71:J71) -> 0
A72: Demande abandonnée | D72: 0 | E72: 0 | F72: 0 | G72: 0 | H72: 0 | I72: 0 | J72: 0 | K72: =SUM(D72:J72) -> 0 | AA72: =SUM(W121,S138,#REF!) -> #REF!
A73: Ni confirmée ni infirmée | D73: 0 | E73: 0 | F73: 0 | G73: 0 | H73: 0 | I73: 0 | J73: 0 | K73: =SUM(D73:J73) -> 0 | AA73: =SUM(W122,S139,#REF!) -> #REF!
A74: Total | D74: =SUM(D67:D73) -> 0 | E74: =SUM(E67:E73) -> 0 | F74: =SUM(F67:F73) -> 0 | G74: =SUM(G67:G73) -> 0 | H74: =SUM(H67:H73) -> 0 | I74: =SUM(I67:I73) -> 0 | J74: =SUM(J67:J73) -> 0 | K74: =SUM(K67:K73) -> 0 | L74: =IF(K74<>H20,"""Total"" doit être égal au ""Fermées pendant la période d'établissement de rapport""","") | AA74: =SUM(W123,S140,#REF!) -> #REF!
K75: =SUM(K67:K70,K72:K73) -> 0
A77: 3.2 Exceptions
A79: Article | C79: Nombre de demandes | E79: Article | G79: Nombre de demandes | I79: Article | K79: Nombre de demandes
A80: 18(2) | C80: 0 | E80: 22(1)a)(i) | G80: 0 | I80: 23a) | K80: 0
A81: 19(1)a) | C81: 0 | E81: 22(1)a)(ii) | G81: 0 | I81: 23b) | K81: 0
A82: 19(1)b) | C82: 0 | E82: 22(1)a)(iii) | G82: 0 | I82: 24a) | K82: 0
A83: 19(1)c) | C83: 0 | E83: 22(1)b) | G83: 0 | I83: 24b) | K83: 0
A84: 19(1)d) | C84: 0 | E84: 22(1)c) | G84: 0 | I84: 25 | K84: 0
A85: 19(1)e) | C85: 0 | E85: 22(2) | G85: 0 | I85: 26 | K85: 0
A86: 19(1)f) | C86: 0 | E86: 22.1 | G86: 0 | I86: 27 | K86: 0
A87: 20 | C87: 0 | E87: 22.2 | G87: 0 | I87: 27.1 | K87: 0
A88: 21 | C88: 0 | E88: 22.3 | G88: 0 | I88: 28 | K88: 0
E89: 22.4 | G89: 0
A91: 3.3 Exclusions
A93: Article | C93: Nombre de demandes | E93: Article | G93: Nombre de demandes | I93: Article | K93: Nombre de demandes
A94: 69(1)a) | C94: 0 | E94: 70(1) | G94: 0 | I94: 70(1)d) | K94: 0
A95: 69(1)b) | C95: 0 | E95: 70(1)a) | G95: 0 | I95: 70(1)e) | K95: 0
A96: 69.1 | C96: 0 | E96: 70(1)b) | G96: 0 | I96: 70(1)f) | K96: 0
E97: 70(1)c) | G97: 0 | I97: 70.1 | K97: 0
A99: 3.4 Format des documents communiqués
A101: Papier | C101: Électronique | H101: Autres
C102: Document électronique | E102: Ensemble de données | F102: Vidéo | G102: Audio
A103: 0 | C103: 0 | E103: 0 | F103: 0 | G103: 0 | H103: 0
A105: 3.5 Complexité
A107: 3.5.1 Pages pertinentes traitées et communiquées en formats papier, document électronique et ensemble de données
A109: Nombre de pages traitées | D109: Nombre de pages communiquées | G109: Nombre de demandes
A110: 0 | D110: 0 | G110: 0
A112: 3.5.2 Pages pertinentes traitées en fonction de l’ampleur des demandes en formats papier, document électronique et ensemble de données par disposition des demandes
A115: Disposition | C115: Moins de 500 pages traitées | E115: 500 à 10 000 pages traitées | G115: Plus de 10 000 pages traitées
C116: Nombre de demandes | D116: Pages traitées | E116: Nombre de demandes | F116: Pages traitées | G116: Nombre de demandes | H116: Pages traitées
A117: Communication totale | C117: 0 | D117: 0 | E117: 0 | F117: 0 | G117: 0 | H117: 0
A118: Communication partielle | C118: 0 | D118: 0 | E118: 0 | F118: 0 | G118: 0 | H118: 0
A119: Exception totale | C119: 0 | D119: 0 | E119: 0 | F119: 0 | G119: 0 | H119: 0
A120: Exclusion totale | C120: 0 | D120: 0 | E120: 0 | F120: 0 | G120: 0 | H120: 0
A121: Demande abandonnée | C121: 0 | D121: 0 | E121: 0 | F121: 0 | G121: 0 | H121: 0
A122: Ni confirmée ni infirmée | C122: 0 | D122: 0 | E122: 0 | F122: 0 | G122: 0 | H122: 0
A123: Total | C123: =SUM(C117:C122) -> 0 | D123: =SUM(D117:D122) -> 0 | E123: =SUM(E117:E122) -> 0 | F123: =SUM(F117:F122) -> 0 | G123: =SUM(G117:G122) -> 0 | H123: =SUM(H117:H122) -> 0 | I123: =IF(G110<>SUM(C123,E123,G123),"Section 3.5.2 - La somme des Colonnes ""Nombre de demandes"" de ""Total"" doit être égale au ""Nombre de demandes"" de la Section 3.5.1.","")
I124: =IF(A110<>SUM(D123,F123,H123),"Section 3.5.2 - La somme des Colonnes ""Pages traitées"" doit être égale au ""Nombre de page traitées"" de la Section 3.5.1.","")
A125: 3.5.3 Minutes pertinentes traitées et communiquées en format audio et vidéo
A127: Nombre de minutes traitées | D127: Nombre de minutes communiquées | G127: Nombre de demandes
A128: 0 | D128: 0 | G128: 0
A130: 3.5.4 Minutes pertinentes traitées en fonction de l'ampleur des demandes en format audio et vidéo par dispositions des demandes
A132: Disposition | D132: Nombre de demandes | G132: Minutes traitées
A134: Communication totale | D134: 0 | G134: 0 | S134: =SUM(D134,#REF!,#REF!) -> #REF!
A135: Communication partielle | D135: 0 | G135: 0 | S135: =SUM(D135,#REF!,#REF!) -> #REF!
...

Sheet ATI_ForConsumption
A1: Inst | B1: =LAI!D6 -> 0
A2: Report | B2: 2021;2022
A3: Q1R1C1 | B3: =LAI!H14 -> 0 | C3: 1,1
A4: Q1R2C1 | B4: =LAI!H15 -> 0 | C4: 1,1
A5: Q1R3C1 | B5: =LAI!G16 -> 0 | C5: 1,1
A6: Q1R4C1 | B6: =LAI!G17 -> 0 | C6: 1,1
A7: Q1R5C1 | B7: =LAI!H18 -> 0 | C7: 1,1
A8: Q1R6C1 | B8: =LAI!H19 -> 0 | C8: 1,1
A9: Q1R7C1 | B9: =LAI!H20 -> 0 | C9: 1,1
A10: Q1R8C1 | B10: =LAI!G21 -> 0 | C10: 1,1
A11: Q1R9C1 | B11: =LAI!G22 -> 0 | C11: 1,1
A12: Q2R1C1 | B12: =LAI!G27 -> 0 | C12: 1,2
A13: Q2R2C1 | B13: =LAI!G28 -> 0 | C13: 1,2
A14: Q2R3C1 | B14: =LAI!G29 -> 0 | C14: 1,2
A15: Q2R4C1 | B15: =LAI!G30 -> 0 | C15: 1,2
A16: Q2R5C1 | B16: =LAI!G31 -> 0 | C16: 1,2
A17: Q2R6C1 | B17: =LAI!G32 -> 0 | C17: 1,2
A18: Q2R7C1 | B18: =LAI!G33 -> 0 | C18: 1,2
A19: Q3R1C1 | B19: =LAI!G38 -> 0 | C19: 1,3
A20: Q3R2C1 | B20: =LAI!G39 -> 0 | C20: 1,3
A21: Q3R3C1 | B21: =LAI!G40 -> 0 | C21: 1,3
A22: Q3R4C1 | B22: =LAI!G41 -> 0 | C22: 1,3
A23: Q3R5C1 | B23: =LAI!G42 -> 0 | C23: 1,3
A24: Q3R6C1 | B24: =LAI!G43 -> 0 | C24: 1,3
A25: Q3R7C1 | B25: =LAI!G44 -> 0 | C25: 1,3
A26: Q4R1C1 | B26: =LAI!H50 -> 0 | C26: 2,1
A27: Q4R2C1 | B27: =LAI!H51 -> 0 | C27: 2,1
A28: Q4R3C1 | B28: =LAI!G52 -> 0 | C28: 2,1
A29: Q4R4C1 | B29: =LAI!G53 -> 0 | C29: 2,1
A30: Q4R5C1 | B30: =LAI!H54 -> 0 | C30: 2,1
A31: Q4R6C1 | B31: =LAI!H55 -> 0 | C31: 2,1
A32: Q4R7C1 | B32: =LAI!H56 -> 0 | C32: 2,1
A33: Q5R1C1 | B33: =LAI!#REF! -> #REF! | C33: 2,2
A34: Q5R2C1 | B34: =LAI!#REF! -> #REF! | C34: 2,2
A35: Q5R3C1 | B35: =LAI!#REF! -> #REF! | C35: 2,2
A36: Q5R4C1 | B36: =LAI!#REF! -> #REF! | C36: 2,2
A37: Q5R5C1 | B37: =LAI!#REF! -> #REF! | C37: 2,2
A38: Q5R6C1 | B38: =LAI!#REF! -> #REF! | C38: 2,2
A39: Q5R7C1 | B39: =LAI!#REF! -> #REF! | C39: 2,2
A40: Q6R1C1 | B40: =LAI!A62 -> 0 | C40: 2,3
A41: Q6R1C2 | B41: =LAI!B62 -> 0 | C41: 2,3
A42: Q6R1C3 | B42: =LAI!C62 -> 0 | C42: 2,3
A43: Q6R1C4 | B43: =LAI!D62 -> 0 | C43: 2,3
A44: Q6R1C5 | B44: =LAI!E62 -> 0 | C44: 2,3
A45: Q6R1C6 | B45: =LAI!F62 -> 0 | C45: 2,3
A46: Q6R1C7 | B46: =LAI!G62 -> 0 | C46: 2,3
A47: Q7R1C1 | B47: =LAI!#REF! -> #REF! | C47: 2,4
A48: Q7R1C2 | B48: =LAI!#REF! -> #REF! | C48: 2,4
A49: Q7R1C3 | B49: =LAI!#REF! -> #REF! | C49: 2,4
A50: Q7R1C4 | B50: =LAI!#REF! -> #REF! | C50: 2,4
A51: Q7R1C5 | B51: =LAI!#REF! -> #REF! | C51: 2,4
A52: Q7R1C6 | B52: =LAI!#REF! -> #REF! | C52: 2,4
A53: Q7R1C7 | B53: =LAI!#REF! -> #REF! | C53: 2,4
A54: Q7R1C8 | B54: =LAI!#REF! -> #REF! | C54: 2,4
A55: Q7R1C9 | B55: =LAI!#REF! -> #REF! | C55: 2,4
A56: Q7R1C10 | B56: =LAI!#REF! -> #REF! | C56: 2,4
A57: Q8R1C1 | B57: =LAI!A68 -> 0 | C57: 2,5
A58: Q8R1C2 | B58: =LAI!B68 -> 0 | C58: 2,5
A59: Q8R1C3 | B59: =LAI!#REF! -> #REF! | C59: 2,5
A60: Q8R1C4 | B60: =LAI!#REF! -> #REF! | C60: 2,5
A61: Q8R1C5 | B61: =LAI!C68 -> 0 | C61: 2,5
A62: Q8R1C6 | B62: =LAI!D68 -> 0 | C62: 2,5
A63: Q8R1C7 | B63: =LAI!#REF! -> #REF! | C63: 2,5
A64: Q8R1C8 | B64: =LAI!#REF! -> #REF! | C64: 2,5
A65: Q8R1C9 | B65: =LAI!E68 -> 0 | C65: 2,5
A66: Q8R1C10 | B66: =LAI!F68 -> 0 | C66: 2,5
A67: Q9R1C1 | B67: =LAI!H73 -> 0 | C67: 3
A68: Q9R2C1 | B68: =LAI!H74 -> 0 | C68: 3
A69: Q9R3C1 | B69: =LAI!H75 -> 0 | C69: 3
A70: Q9R4C1 | B70: =LAI!H76 -> 0 | C70: 3
A71: Q9R5C1 | B71: =LAI!H77 -> 0 | C71: 3
A72: Q9R6C1 | B72: =LAI!H78 -> 0 | C72: 3
A73: Q9R7C1 | B73: =LAI!H79 -> 0 | C73: 3
A74: Q10R1C1 | B74: =LAI!E87 -> 0 | C74: 4,1
A75: Q10R1C2 | B75: =LAI!F87 -> 0 | C75: 4,1
A76: Q10R1C3 | B76: =LAI!G87 -> 0 | C76: 4,1
A77: Q10R1C4 | B77: =LAI!H87 -> 0 | C77: 4,1
A78: Q10R1C5 | B78: =LAI!I87 -> 0 | C78: 4,1
A79: Q10R1C6 | B79: =LAI!J87 -> 0 | C79: 4,1
A80: Q10R1C7 | B80: =LAI!K87 -> 0 | C80: 4,1
A81: Q10R2C1 | B81: =LAI!E88 -> 0 | C81: 4,1
A82: Q10R2C2 | B82: =LAI!F88 -> 0 | C82: 4,1
A83: Q10R2C3 | B83: =LAI!G88 -> 0 | C83: 4,1
A84: Q10R2C4 | B84: =LAI!H88 -> 0 | C84: 4,1
A85: Q10R2C5 | B85: =LAI!I88 -> 0 | C85: 4,1
A86: Q10R2C6 | B86: =LAI!J88 -> 0 | C86: 4,1
A87: Q10R2C7 | B87: =LAI!K88 -> 0 | C87: 4,1
A88: Q10R3C1 | B88: =LAI!E89 -> 0 | C88: 4,1
A89: Q10R3C2 | B89: =LAI!F89 -> 0 | C89: 4,1
A90: Q10R3C3 | B90: =LAI!G89 -> 0 | C90: 4,1
A91: Q10R3C4 | B91: =LAI!H89 -> 0 | C91: 4,1
A92: Q10R3C5 | B92: =LAI!I89 -> 0 | C92: 4,1
A93: Q10R3C6 | B93: =LAI!J89 -> 0 | C93: 4,1
A94: Q10R3C7 | B94: =LAI!K89 -> 0 | C94: 4,1
A95: Q10R4C1 | B95: =LAI!E90 -> 0 | C95: 4,1
A96: Q10R4C2 | B96: =LAI!F90 -> 0 | C96: 4,1
A97: Q10R4C3 | B97: =LAI!G90 -> 0 | C97: 4,1
A98: Q10R4C4 | B98: =LAI!H90 -> 0 | C98: 4,1
A99: Q10R4C5 | B99: =LAI!I90 -> 0 | C99: 4,1
A100: Q10R4C6 | B100: =LAI!J90 -> 0 | C100: 4,1
...

Sheet Privacy_ForConsumption
A1: Inst | B1: =LPRP!H6 -> 0
A2: Report | B2: 2021;2022
A3: Q1R1C1 | B3: =LPRP!H15 -> 0 | C3: 1,1
A4: Q1R2C1 | B4: =LPRP!H16 -> 0 | C4: 1,1
A5: Q1R3C1 | B5: =LPRP!G17 -> 0 | C5: 1,1
A6: Q1R4C1 | B6: =LPRP!G18 -> 0 | C6: 1,1
A7: Q1R5C1 | B7: =LPRP!H19 -> 0 | C7: 1,1
A8: Q1R6C1 | B8: =LPRP!H20 -> 0 | C8: 1,1
A9: Q1R7C1 | B9: =LPRP!H21 -> 0 | C9: 1,1
A10: Q1R8C1 | B10: =LPRP!G22 -> 0 | C10: 1,1
A11: Q1R9C1 | B11: =LPRP!G23 -> 0 | C11: 1,1
A12: Q2R1C1 | B12: =LPRP!G28 -> 0 | C12: 1,2
A13: Q2R2C1 | B13: =LPRP!G29 -> 0 | C13: 1,2
A14: Q2R3C1 | B14: =LPRP!G30 -> 0 | C14: 1,2
A15: Q2R4C1 | B15: =LPRP!G31 -> 0 | C15: 1,2
A16: Q2R5C1 | B16: =LPRP!G32 -> 0 | C16: 1,2
A17: Q2R6C1 | B17: =LPRP!G33 -> 0 | C17: 1,2
A18: Q2R7C1 | B18: =LPRP!G34 -> 0 | C18: 1,2
A19: Q3R1C1 | B19: =LPRP!H40 -> 0 | C19: 2,1
A20: Q3R2C1 | B20: =LPRP!H41 -> 0 | C20: 2,1
A21: Q3R3C1 | B21: =LPRP!G42 -> 0 | C21: 2,1
A22: Q3R4C1 | B22: =LPRP!G43 -> 0 | C22: 2,1
A23: Q3R5C1 | B23: =LPRP!H44 -> 0 | C23: 2,1
A24: Q3R6C1 | B24: =LPRP!H45 -> 0 | C24: 2,1
A25: Q3R7C1 | B25: =LPRP!H46 -> 0 | C25: 2,1
A26: Q4R1C1 | B26: =LPRP!#REF! -> #REF! | C26: 2,2
A27: Q4R2C1 | B27: =LPRP!#REF! -> #REF! | C27: 2,2
A28: Q4R3C1 | B28: =LPRP!#REF! -> #REF! | C28: 2,2
A29: Q4R4C1 | B29: =LPRP!#REF! -> #REF! | C29: 2,2
A30: Q4R5C1 | B30: =LPRP!#REF! -> #REF! | C30: 2,2
A31: Q4R6C1 | B31: =LPRP!#REF! -> #REF! | C31: 2,2
A32: Q4R7C1 | B32: =LPRP!#REF! -> #REF! | C32: 2,2
A33: Q5R1C1 | B33: =LPRP!A52 -> 0 | C33: 2,3
A34: Q5R1C2 | B34: =LPRP!B52 -> 0 | C34: 2,3
A35: Q5R1C3 | B35: =LPRP!C52 -> 0 | C35: 2,3
A36: Q5R1C4 | B36: =LPRP!D52 -> 0 | C36: 2,3
A37: Q5R1C5 | B37: =LPRP!E52 -> 0 | C37: 2,3
A38: Q5R1C6 | B38: =LPRP!F52 -> 0 | C38: 2,3
A39: Q5R1C7 | B39: =LPRP!G52 -> 0 | C39: 2,3
A40: Q6R1C1 | B40: =LPRP!A58 -> 0 | C40: 2,4
A41: Q6R1C2 | B41: =LPRP!B58 -> 0 | C41: 2,4
A42: Q6R1C3 | B42: =LPRP!#REF! -> #REF! | C42: 2,4
A43: Q6R1C4 | B43: =LPRP!#REF! -> #REF! | C43: 2,4
A44: Q6R1C5 | B44: =LPRP!C58 -> 0 | C44: 2,4
A45: Q6R1C6 | B45: =LPRP!D58 -> 0 | C45: 2,4
A46: Q6R1C7 | B46: =LPRP!#REF! -> #REF! | C46: 2,4
A47: Q6R1C8 | B47: =LPRP!#REF! -> #REF! | C47: 2,4
A48: Q6R1C9 | B48: =LPRP!E58 -> 0 | C48: 2,4
A49: Q6R1C10 | B49: =LPRP!F58 -> 0 | C49: 2,4
A50: Q7R1C1 | B50: =LPRP!D67 -> 0 | C50: 3,1
A51: Q7R1C2 | B51: =LPRP!E67 -> 0 | C51: 3,1
A52: Q7R1C3 | B52: =LPRP!F67 -> 0 | C52: 3,1
A53: Q7R1C4 | B53: =LPRP!G67 -> 0 | C53: 3,1
A54: Q7R1C5 | B54: =LPRP!H67 -> 0 | C54: 3,1
A55: Q7R1C6 | B55: =LPRP!I67 -> 0 | C55: 3,1
A56: Q7R1C7 | B56: =LPRP!J67 -> 0 | C56: 3,1
A57: Q7R2C1 | B57: =LPRP!D68 -> 0 | C57: 3,1
A58: Q7R2C2 | B58: =LPRP!E68 -> 0 | C58: 3,1
A59: Q7R2C3 | B59: =LPRP!F68 -> 0 | C59: 3,1
A60: Q7R2C4 | B60: =LPRP!G68 -> 0 | C60: 3,1
A61: Q7R2C5 | B61: =LPRP!H68 -> 0 | C61: 3,1
A62: Q7R2C6 | B62: =LPRP!I68 -> 0 | C62: 3,1
A63: Q7R3C7 | B63: =LPRP!J68 -> 0 | C63: 3,1
A64: Q7R3C1 | B64: =LPRP!D69 -> 0 | C64: 3,1
A65: Q7R3C2 | B65: =LPRP!E69 -> 0 | C65: 3,1
A66: Q7R3C3 | B66: =LPRP!F69 -> 0 | C66: 3,1
A67: Q7R3C4 | B67: =LPRP!G69 -> 0 | C67: 3,1
A68: Q7R3C5 | B68: =LPRP!H69 -> 0 | C68: 3,1
A69: Q7R3C6 | B69: =LPRP!I69 -> 0 | C69: 3,1
A70: Q7R3C7 | B70: =LPRP!J69 -> 0 | C70: 3,1
A71: Q7R4C1 | B71: =LPRP!D70 -> 0 | C71: 3,1
A72: Q7R4C2 | B72: =LPRP!E70 -> 0 | C72: 3,1
A73: Q7R4C3 | B73: =LPRP!F70 -> 0 | C73: 3,1
A74: Q7R4C4 | B74: =LPRP!G70 -> 0 | C74: 3,1
A75: Q7R4C5 | B75: =LPRP!H70 -> 0 | C75: 3,1
A76: Q7R4C6 | B76: =LPRP!I70 -> 0 | C76: 3,1
A77: Q7R4C7 | B77: =LPRP!J70 -> 0 | C77: 3,1
A78: Q7R5C1 | B78: =LPRP!D71 -> 0 | C78: 3,1
A79: Q7R5C2 | B79: =LPRP!E71 -> 0 | C79: 3,1
A80: Q7R5C3 | B80: =LPRP!F71 -> 0 | C80: 3,1
A81: Q7R5C4 | B81: =LPRP!G71 -> 0 | C81: 3,1
A82: Q7R5C5 | B82: =LPRP!H71 -> 0 | C82: 3,1
A83: Q7R5C6 | B83: =LPRP!I71 -> 0 | C83: 3,1
A84: Q7R5C7 | B84: =LPRP!J71 -> 0 | C84: 3,1
A85: Q7R6C1 | B85: =LPRP!D72 -> 0 | C85: 3,1
A86: Q7R6C2 | B86: =LPRP!E72 -> 0 | C86: 3,1
A87: Q7R6C3 | B87: =LPRP!F72 -> 0 | C87: 3,1
A88: Q7R6C4 | B88: =LPRP!G72 -> 0 | C88: 3,1
A89: Q7R6C5 | B89: =LPRP!H72 -> 0 | C89: 3,1
A90: Q7R6C6 | B90: =LPRP!I72 -> 0 | C90: 3,1
A91: Q7R6C7 | B91: =LPRP!J72 -> 0 | C91: 3,1
A92: Q7R7C1 | B92: =LPRP!D73 -> 0 | C92: 3,1
A93: Q7R7C2 | B93: =LPRP!E73 -> 0 | C93: 3,1
A94: Q7R7C3 | B94: =LPRP!F73 -> 0 | C94: 3,1
A95: Q7R7C4 | B95: =LPRP!G73 -> 0 | C95: 3,1
A96: Q7R7C5 | B96: =LPRP!H73 -> 0 | C96: 3,1
A97: Q7R7C6 | B97: =LPRP!I73 -> 0 | C97: 3,1
A98: Q7R7C7 | B98: =LPRP!J73 -> 0 | C98: 3,1
A99: Q8R1C1 | B99: =LPRP!C80 -> 0 | C99: 3,2
A100: Q8R2C1 | B100: =LPRP!C81 -> 0 | C100: 3,2
...
