Workbook

Sheet LAI
AA1: jdurand - 2022-05-16 14:34
A4: Rapport statistique sur la Loi sur l’accès à l’information
A6: Nom de l’institution: | D6: Défense nationale | K6: Vous devez entrer le nom d'une institution
A8: 45017 | F8: 45383 | H8: 45382 | I8: 45747
A10: Section 1 – Demandes en vertu de la Loi sur l’accès à l’information
A12: 1.1 Nombre de demandes
H13: Nombre de demandes
A14: Reçues pendant la période d'établissement de rapport | H14: 2347
A15: En suspens à la fin de la période d'établissement de rapport précédente | H15: =G16+G17
A16: • En suspens à la fin de la période d'établissement de rapport précédente | G16: 183
A17: • En suspens pour plus d'une période d'établissement de rapport | G17: 1594
A18: Total | H18: =H14+H15
A19: Fermées pendant la période d'établissement de rapport | H19: 2086
A20: Reportées à la prochaine période d'établissement de rapport | H20: =SUM(G21:G22) | M20: Section 1.1 - Le montant "Reportées à la prochaine période d'établissement de rapport" doit être égal au "Total" moins "Fermées pendant la période d'établissement de rapport".
A21: • Reportées à la prochaine période d'établissement de rapport dans les délais prévus par la Loi | G21: 186
A22: • Reportées à la prochaine période d'établissement de rapport au-delà des délais prévus par la Loi | G22: 1852
A24: 1.2 Source des demandes
A26: Source | G26: Nombre de demandes
A27: Médias | G27: 486
A28: Secteur universitaire | G28: 74
A29: Secteur commercial (secteur privé) | G29: 134
A30: Organisation | G30: 21
A31: Public | G31: 1536
A32: Refus de s'identifier | G32: 96 | M32: Section 1.2 - Le "Total" doit être égal au montant "Reçues pendant la période d'établissement de rapport" de la Section 1.1
A33: Total | G33: =SUM(G27:J32)
A35: 1.3 Mode des demandes
A37: Mode | G37: Nombre des demandes
A38: En ligne | G38: 2217
A39: Courriel | G39: 60
A40: Poste | G40: 70
A41: En personne | G41: 0
A42: Téléphone | G42: 0
A43: Télécopieur | G43: 0 | M43: Section 1.3 - Le "Total" doit être égal au montant "Reçues pendant la période d'établissement de rapport" de la Section 1.1
A44: Total | G44: =SUM(G38:J43)
A46: Section 2 – Demandes informelles
A48: 2.1 Nombre de demandes informelles
H49: Nombre de demandes
A50: Reçues pendant la période d'établissement de rapport | H50: 969
A51: En suspens à la fin de la période d'établissement de rapport précédente | H51: =SUM(G52:G53)
A52: • En suspens à la fin de la période d'établissement de rapport précédente | G52: 86
A53: • En suspens pour plus d'une période d'établissement de rapport | G53: 3
A54: Total | H54: =SUM(H50:J51)
A55: Fermées pendant la période d'établissement de rapport | H55: 1011
A56: Reportées à la prochaine période d'établissement de rapport | H56: =H54-H55
A58: 2.2 Mode des demandes informelles
A60: Mode | G60: Nombre des demandes
A61: En ligne | G61: 281
A62: Courriel | G62: 678
A63: Poste | G63: 10
A64: En personne | G64: 0
A65: Téléphone | G65: 0
A66: Télécopieur | G66: 0 | M66: Section 2.2 - Le "Total" doit être égal au montant "Reçues pendant la période d'établissement de rapport" de la Section 2.1
A67: Total | G67: =SUM(G61:J66)
A69: 2.3 Délai de traitement pour les demandes informelles
A71: Délai de traitement
A72: 0 à 15 jours | B72: 16 à 30 jours | C72: 31 à 60 jours | D72: 61 à 120 jours | E72: 121 à 180 jours | F72: 181 à 365 jours | G72: Plus de 365 jours | H72: Total
A73: 875 | B73: 107 | C73: 4 | D73: 12 | E73: 10 | F73: 0 | G73: 3 | H73: =SUM(A73:G73) | M73: Section 2.3 - Le "Total" doit être égal au montant "Fermées pendant la période d'établissement de rapport" de la Section 2.1
A75: 2.4 Pages communiquées informellement | M75: =IFERROR(IF(B79/A79>99,"Section 2.4 - Le nombre total de pages ""Pages communiquées"" divisé par le ""Nombre de demandes"" dans ""Moins de 100 pages communiquées"" doit être égal ou inférieur à 99.",""),"")
M76: =IFERROR(IF(AND(D79/C79>=100,D79/C79<=500),"","Section 2.4 - Le nombre total de pages ""Pages communiquées"" divisé par le ""Nombre de demandes"" dans ""De 100 à 500 pages communiquées"" doit être compris entre 100 et 500."),"")
A77: Moins de 100 pages communiquées | C77: De 100 à 500 pages communiquées | E77: De 501 à 1 000 pages communiquées | G77: De 1 001 à 5 000 pages communiquées | I77: Plus de 5 000 pages communiquées | M77: =IFERROR(IF(AND(F79/E79>500,F79/E79<=1000),"","Section 2.4 - Le nombre total de pages ""Pages communiquées"" divisé par le ""Nombre de demandes"" dans ""De 501 à 1 000 pages communiquées"" doit être compris entre 501 et 1 000."),"")
A78: Nombre de demandes | B78: Pages communiquées | C78: Nombre de demandes | D78: Pages communiquées | E78: Nombre de demandes | F78: Pages communiquées | G78: Nombre de demandes | H78: Pages communiquées | I78: Nombre de demandes | J78: Pages communiquées | M78: Section 2.4 - La somme des Colonnes "Nombre de demandes" doit être égale ou inférieure au montant "Fermées pendant la période d'établissement de rapport" de la Section 2.1
A79: 0 | B79: 0 | C79: 0 | D79: 0 | E79: 0 | F79: 0 | G79: 0 | H79: 0 | I79: 0 | J79: 0 | M79: Section 2.4 - La somme des Colonnes "Nombre de demandes" des Sections 2.4 et 2.5 doit être égale au montant "Fermées pendant la période d'établissement de rapport" de la Section 2.1
M80: =IFERROR(IF(AND(H79/G79>1000,H79/G79<=5000),"","Section 2.4 - Le nombre total de pages ""Pages communiquées"" divisé par le ""Nombre de demandes"" dans ""De 1 001 à 5 000 pages communiquées"" doit être compris entre 1 0001 et 5 000."),"")
A81: 2.5 Pages recommuniquées informellement | M81: =IFERROR(IF(J79/I79<=5000,"Section 2.4 - Le nombre total de pages ""Pages communiquées"" divisé par le ""Nombre de demandes"" dans ""Plus de 5 000 pages communiquées"" doit être supérieur à 5 000.",""),"")
M82: =IFERROR(IF(B85/A85>99,"Section 2.5 - Le nombre total de pages ""Pages recommuniquées"" divisé par le ""Nombre de demandes"" dans ""Moins de 100 pages recommuniquées"" doit être égal ou inférieur à 99.",""),"")
A83: Moins de 100 pages recommuniquées | C83: De 100 à 500 pages recommuniquées | E83: De 501 à 1 000 pages recommuniquées | G83: De 1 001 à 5 000 pages recommuniquées | I83: Plus de 5 000 pages recommuniquées | M83: =IFERROR(IF(AND(D85/C85>=100,D85/C85<=500),"","Section 2.5 - Le nombre total de pages ""Pages recommuniquées"" divisé par le ""Nombre de demandes"" dans ""De 100 à 500 pages recommuniquées"" doit être compris entre 100 et 500."),"")
A84: Nombre de demandes | B84: Pages recommuniquées | C84: Nombre de demandes | D84: Pages recommuniquées | E84: Nombre de demandes | F84: Pages recommuniquées | G84: Nombre de demandes | H84: Pages recommuniquées | I84: Nombre de demandes | J84: Pages recommuniquées | M84: Section 2.5 - La somme des Colonnes "Nombre de demandes" doit être égale ou inférieur au montant "Fermées pendant la période d'établissement de rapport" de la Section 2.1
A85: 664 | B85: 14866 | C85: 227 | D85: 48889 | E85: 67 | F85: 50296 | G85: 46 | H85: 83495 | I85: 7 | J85: 68024 | M85: Section 2.5 - La somme des Colonnes "Nombre de demandes" des Sections 2.4 et 2.5 doit être égale au montant "Fermées pendant la période d'établissement de rapport" de la Section 2.1
A87: Section 3 – Demandes à la Commissaire à l'information pour ne pas donner suite à la demande | M87: =IFERROR(IF(AND(F85/E85>500,F85/E85<=1000),"","Section 2.5 - Le nombre total de pages ""Pages recommuniquées"" divisé par le ""Nombre de demandes"" dans ""De 501 à 1 000 pages recommuniquées"" doit être compris entre 501 et 1 000."),"")
M88: =IFERROR(IF(AND(H85/G85>1000,H85/G85<=5000),"","Section 2.5 - Le nombre total de pages ""Pages recommuniquées"" divisé par le ""Nombre de demandes"" dans ""De 1 001 à 5 000 pages recommuniquées"" doit être compris entre 1 0001 et 5 000."),"")
H89: Nombre de demandes | M89: =IFERROR(IF(J85/I85<=5000,"Section 2.5 - Le nombre total de pages ""Pages recommuniquées"" divisé par le ""Nombre de demandes"" dans ""Plus de 5 000 pages recommuniquées"" doit être supérieur à 5 000.",""),"")
A90: En suspens depuis la période d’établissement de rapports précédente | H90: 0
A91: Envoyées pendant la période d’établissement de rapports | H91: 0
A92: Total | H92: =SUM(H90:K91)
A93: Approuvées par la Commissaire à l’information pendant la période d’établissement de rapports | H93: 0
A94: Refusées par la Commissaire à l’information au cours de la période d’établissement de rapports | H94: 0
A95: Retirées pendant la période d'établissement de rapports | H95: 0 | L95: =IF(SUM(H93:K96)-H92<>0,"Section 3 - Le montant ""Reportées à la prochaine période"" doit être égal au ""Total"" moins ""Approuvées par la Commissaire"" moins ""Refusées par la Commissaire "" moins ""Retirées pendant la période"" de la Section 3","")
A96: Reportées à la prochaine période d’établissement de rapports | H96: 0
A98: Section 4 – Demandes fermées pendant la période d'établissement de rapports
A100: 4.1 Disposition et délai de traitement | M100: =IF(L105>SUM(C118:C135,F118:F133,I118:I131,L118:L130,C140:D145,G140:H146,K140:L146),"Le nombre total de demandes indiqué dans ""Communication partielle"" doit être égal ou inférieur au nombre total de demandes indiqué aux tableaux 4.2 et 4.3.","")
M101: =IF(L106>SUM(C118:C135,F118:F133,I118:I131,L118:L130),"Le nombre total de demandes indiqué dans ""Exception totale"" doit être égal ou inférieur au nombre total de demandes indiqué au tableau 4.2.","")
A102: Disposition des demandes | E102: Délai de traitement | M102: =IF(L107>SUM(C140:D145,G140:H146,K140:L146),"Le nombre total de demandes indiqué dans ""Exclusion totale"" doit être égal ou inférieur au nombre total de demandes indiqué au tableau 4.3. ","")
E103: 0 à 15 jours | F103: 16 à 30 jours | G103: 31 à 60 jours | H103: 61 à 120 jours | I103: 121 à 180 jours | J103: 181 à 365 jours | K103: Plus de 365 jours | L103: Total | X103: Nombre de demandes | Y103: Pages traitées
A104: Communication totale | E104: 2 | F104: 15 | G104: 21 | H104: 28 | I104: 17 | J104: 32 | K104: 60 | L104: =SUM(E104:K104) | X104: =SUM(V166,Y184,AC202) | Y104: =SUM(W166,Z184,AD202)
A105: Communication partielle | E105: 175 | F105: 0 | G105: 19 | H105: 34 | I105: 76 | J105: 36 | K105: 97 | L105: =SUM(E105:K105) | X105: =SUM(V167,Y185,AC203) | Y105: =SUM(W167,Z185,AD203)
A106: Exception totale | E106: 323 | F106: 585 | G106: 0 | H106: 4 | I106: 3 | J106: 4 | K106: 0 | L106: =SUM(E106:K106) | X106: =SUM(V168,Y186,AC204) | Y106: =SUM(W168,Z186,AD204)
A107: Exclusion totale | E107: 4 | F107: 8 | G107: 23 | H107: 0 | I107: 0 | J107: 0 | K107: 0 | L107: =SUM(E107:K107) | X107: =SUM(V169,Y187,AC205) | Y107: =SUM(W169,Z187,AD205)
A108: Aucun document n’existe | E108: 0 | F108: 0 | G108: 2 | H108: 2 | I108: 788 | J108: 49 | K108: 26 | L108: =SUM(E108:K108)
A109: Demande transférée | E109: 35 | F109: 9 | G109: 15 | H109: 13 | I109: 935 | J109: 18 | K109: 2 | L109: =SUM(E109:K109)
A110: Demande abandonnée | E110: 0 | F110: 0 | G110: 0 | H110: 0 | I110: 0 | J110: 20 | K110: 226 | L110: =SUM(E110:K110) | X110: =SUM(V170,Y188,AC206) | Y110: =SUM(W170,Z188,AD206)
A111: Ni confirmée ni infirmée | E111: 15 | F111: 8 | G111: 4 | H111: 2 | I111: 6 | J111: 83 | K111: 344 | L111: =SUM(E111:K111) | X111: =SUM(V171,Y189,AC207) | Y111: =SUM(W171,Z189,AD207)
A112: Refus d'agir avec l'approbation de la Commissaire à l'information | E112: 0 | F112: 0 | G112: 0 | H112: 0 | I112: 0 | J112: 0 | K112: 2 | L112: =SUM(E112:K112) | M112: Section 4.1 - Le "Total" des demandes de la Rangée "Refus d'agir avec l'approbation de la Commissaire à l'information" doit être égal au montant "Approuvées par la Commissaire à l’information pendant la période d’établissement de rapports" de la Section 3 | X112: =SUM(V172,Y190,AC208) | Y112: =SUM(W172,Z190,AD208)
A113: Total | E113: =SUM(E104:E112) | F113: =SUM(F104:F112) | G113: =SUM(G104:G112) | H113: =SUM(H104:H112) | I113: =SUM(I104:I112) | J113: =SUM(J104:J112) | K113: =SUM(K104:K112) | L113: =SUM(L104:L112) | M113: Section 4.1 - La somme des totaux de la Rangée 10 doit être égale au montant "Fermées pendant la période d'établissement de rapport" de la Section 1.1
A115: 4.2 Exceptions
A117: Article | C117: Nombre de demandes | D117: Article | F117: Nombre de demandes | G117: Article | I117: Nombre de demandes | J117: Article | L117: Nombre de demandes
A118: 13(1)a) | C118: 36 | D118: 16(2) | F118: 22 | G118: 18a) | I118: 5 | J118: 20.1 | L118: 0
A119: 13(1)b) | C119: 10 | D119: 16(2)a) | F119: 0 | G119: 18b) | I119: 9 | J119: 20.2 | L119: 0
A120: 13(1)c) | C120: 6 | D120: 16(2)b) | F120: 3 | G120: 18c) | I120: 3 | J120: 20.4 | L120: 0
A121: 13(1)d) | C121: 5 | D121: 16(2)c) | F121: 54 | G121: 18d) | I121: 3 | J121: 21(1)a) | L121: 96
A122: 13(1)e) | C122: 0 | D122: 16(3) | F122: 0 | G122: 18.1(1)a) | I122: 0 | J122: 21(1)b) | L122: 69
...

Sheet LPRP
AA1: JDURAND - 2022-05-13 12:05
A4: Rapport statistique sur la Loi sur la protection des renseignements personnels
E6: Nom de l’institution: | O6: Vous devez entrer un nom d'institution
E8: Période d'établissement de rapport : | H8: 45383 | K8: au | L8: 45747
A10: Section 1 – Demandes en vertu de la Loi sur la protection des renseignements personnels
A12: 1.1 Nombre de demandes reçues
H14: Nombre de demandes
A15: Reçues pendant la période d'établissement de rapport | H15: 0
A16: En suspens à la fin de la période d'établissement de rapport précédente | H16: =SUM(G17:G18)
A17: • En suspens à la fin de la période d'établissement de rapport précédente | G17: 0
A18: • En suspens pour plus d'une période d'établissement de rapport | G18: 0
A19: Total | H19: =SUM(H15:J16)
A20: Fermées pendant la période d'établissement de rapport | H20: 0
A21: Reportées à la prochaine période d'établissement de rapport | H21: =SUM(G22:G23) | K21: Section 1.1 - Le montant "Reportées à la prochaine période d'établissement de rapport" doit être égal au "Total" moins "Fermées pendant la période d'établissement de rapport".
A22: • Reportées à la prochaine période d'établissement de rapport dans les délais prévus par la Loi | G22: 0
A23: • Reportées à la prochaine période d'établissement de rapport au-delà des délais prévus par la Loi | G23: 0
A25: 1.2 Mode des demandes
A27: Mode | G27: Nombre des demandes
A28: En ligne | G28: 0
A29: Courriel | G29: 0
A30: Poste | G30: 0
A31: En personne | G31: 0
A32: Téléphone | G32: 0
A33: Télécopieur | G33: 0
A34: Total | G34: =SUM(G28:J33) | K34: Section 1.2 - Le "Total" doit être égal au montant de "Reçues pendant la période d'établissement de rapport" de la Section 1.1
A36: Section 2 – Demandes informelles
A40: 2.1 Nombre de demandes informelles
H41: Nombre de demandes
A42: Reçues pendant la période d'établissement de rapport | H42: 0 | K42: Section 2.1 - Le "Nombre de demandes" "Reçues pendant la période d'établissement de rapport" doit être égal au "Total" de la Section 2.2
A43: En suspens à la fin de la période d'établissement de rapport précédente | H43: =SUM(G44:G45)
A44: • En suspens à la fin de la période d'établissement de rapport précédente | G44: 0
A45: • En suspens pour plus d'une période d'établissement de rapport | G45: 0
A46: Total | H46: =SUM(H42:J43)
A47: Fermées pendant la période d'établissement de rapport | H47: 0
A48: Reportées à la prochaine période d'établissement de rapport | H48: =H46-H47
A50: 2.2 Mode des demandes informelles
A52: Mode | G52: Nombre des demandes
A53: En ligne | G53: 0
A54: Courriel | G54: 0
A55: Poste | G55: 0
A56: En personne | G56: 0
A57: Téléphone | G57: 0
A58: Télécopieur | G58: 0
A59: Total | G59: =SUM(G53:J58) | K59: Section 2.2 - Le "Total" doit être égal au montant "Reçues pendant la période d'établissement de rapport" de la Section 2.1
A61: 2.3 Délai de traitement pour les demandes informelles
A63: Délai de traitement
A64: 0 à 15 jours | B64: 16 à 30 jours | C64: 31 à 60 jours | D64: 61 à 120 jours | E64: 121 à 180 jours | F64: 181 à 365 jours | G64: Plus de 365 jours | H64: Total
A65: 0 | B65: 0 | C65: 0 | D65: 0 | E65: 0 | F65: 0 | G65: 0 | H65: =SUM(A65:G65) | I65: Section 2.3 - Le "Total" doit être égal au montant de "Fermées pendant la période d'établissement de rapport" de la Section 2.1
A67: 2.4 Pages communiquées informellement | K67: =IFERROR(IF(B71/A71>99,"Section 2.4 - Le nombre total de pages ""Pages communiquées"" divisé par le ""Nombre de demandes"" dans ""Moins de 100 pages communiquées"" doit être égal ou inférieur à 99.",""),"")
K68: =IFERROR(IF(AND(D71/C71>=100,D71/C71<=500),"","Section 2.4 - Le nombre total de pages ""Pages communiquées"" divisé par le ""Nombre de demandes"" dans ""De 100 à 500 pages communiquées"" doit être compris entre 100 et 500."),"")
A69: Moins de 100 pages communiquées | C69: De 100 à 500 pages communiquées | E69: De 501 à 1 000 pages communiquées | G69: De 1 001 à 5 000 pages communiquées | I69: Plus de 5 000 pages communiquées | K69: =IFERROR(IF(AND(F71/E71>500,F71/E71<=1000),"","Section 2.4 - Le nombre total de pages ""Pages communiquées"" divisé par le ""Nombre de demandes"" dans ""De 501 à 1 000 pages communiquées"" doit être compris entre 501 et 1 000."),"")
A70: Nombre de demandes | B70: Pages communiquées | C70: Nombre de demandes | D70: Pages communiquées | E70: Nombre de demandes | F70: Pages communiquées | G70: Nombre de demandes | H70: Pages communiquées | I70: Nombre de demandes | J70: Pages communiquées | K70: =IFERROR(IF(AND(H71/G71>1000,H71/G71<=5000),"","Section 2.4 - Le nombre total de pages ""Pages communiquées"" divisé par le ""Nombre de demandes"" dans ""De 1 001 à 5 000 pages communiquées"" doit être compris entre 1 0001 et 5 000."),"")
A71: 0 | B71: 0 | C71: 0 | D71: 0 | E71: 0 | F71: 0 | G71: 0 | H71: 0 | I71: 0 | J71: 0 | K71: Section 2.4 - La somme des Colonnes "Nombre de demandes" doit être égale au montant de "Fermées pendant la période d'établissement de rapport" de la Section 2.1
K73: =IFERROR(IF(J71/I71<=5000,"Section 2.4 - Le nombre total de pages ""Pages communiquées"" divisé par le ""Nombre de demandes"" dans ""Plus de 5 000 pages communiquées"" doit être supérieur à 5 000.",""),"")
A74: Section 3 – Demandes fermées pendant la période d'établissement de rapport
A76: 3.1 Disposition et délai de traitement
L77: =IF(K81>SUM(C93:D101,G93:H102,K93:L101,C107:D109,G107:H110,K107:L110),"Le nombre total de demandes indiqué dans ""Communication partielle"" doit être égal ou inférieur au nombre total de demandes indiqué dans les tableaux 3.2 et 3.3.","")
A78: Disposition des demandes | D78: Délai de traitement | L78: =IF(K82>SUM(C93:D101,G93:H102,K93:L101),"Le nombre total de demandes indiqué dans ""Exception totale"" doit être égal ou inférieur au nombre total de demandes indiqué dans le tableau 3.2.","")
D79: 0 à 15 jours | E79: 16 à 30 jours | F79: 31 à 60 jours | G79: 61 à 120 jours | H79: 121 à 180 jours | I79: 181 à 365 jours | J79: Plus de 365 jours | K79: Total | L79: =IF(K83>SUM(C107:D109,G107:H110,K107:L110),"Le nombre total de demandes indiqué dans ""Exclusion totale"" doit être égal ou inférieur au nombre total de demandes indiqué dans le tableau 3.3.","")
A80: Communication totale | D80: 0 | E80: 0 | F80: 0 | G80: 0 | H80: 0 | I80: 0 | J80: 0 | K80: =SUM(D80:J80) | L80: La somme des Colonnes "Nombre de demandes" en "Communication totale" des Sections 3.5.2, 3.5.4 et 3.5.6 doit être égale ou supérieure au "Total" en "Communication totale" de la Section 3.1 | AA80: =SUM(AA130,AC147,AD164)
A81: Communication partielle | D81: 0 | E81: 0 | F81: 0 | G81: 0 | H81: 0 | I81: 0 | J81: 0 | K81: =SUM(D81:J81) | L81: La somme des Colonnes "Nombre de demandes" en "Communication partielle" des Sections 3.5.2, 3.5.4 et 3.5.6 doit être égale ou supérieure au "Total" en "Communication partielle" de la Section 3.1 | AA81: =SUM(AA131,AC148,AD165)
A82: Exception totale | D82: 0 | E82: 0 | F82: 0 | G82: 0 | H82: 0 | I82: 0 | J82: 0 | K82: =SUM(D82:J82) | L82: La somme des Colonnes "Nombre de demandes" en "Exception totale" des Sections 3.5.2, 3.5.4 et 3.5.6 doit être égale ou supérieure au "Total" en "Exception totale" de la Section 3.1 | AA82: =SUM(AA132,AC149,AD166)
A83: Exclusion totale | D83: 0 | E83: 0 | F83: 0 | G83: 0 | H83: 0 | I83: 0 | J83: 0 | K83: =SUM(D83:J83) | L83: La somme des Colonnes "Nombre de demandes" en "Exclusion totale" des Sections 3.5.2, 3.5.4 et 3.5.6 doit être égale ou supérieure au "Total" en "Exclusion totale" de la Section 3.1 | AA83: =SUM(AA133,AC150,AD167)
A84: Aucun document n’existe | D84: 0 | E84: 0 | F84: 0 | G84: 0 | H84: 0 | I84: 0 | J84: 0 | K84: =SUM(D84:J84)
A85: Demande abandonnée | D85: 0 | E85: 0 | F85: 0 | G85: 0 | H85: 0 | I85: 0 | J85: 0 | K85: =SUM(D85:J85) | L85: La somme des Colonnes "Nombre de demandes" en "Demande abandonnée" des Sections 3.5.2, 3.5.4 et 3.5.6 doit être égale ou supérieure au "Total" en "Demande abandonnée" de la Section 3.1 | AA85: =SUM(AA134,AC151,AD168)
A86: Ni confirmée ni infirmée | D86: 0 | E86: 0 | F86: 0 | G86: 0 | H86: 0 | I86: 0 | J86: 0 | K86: =SUM(D86:J86) | L86: La somme des Colonnes "Nombre de demandes" en "Ni confirmée ni infirmée" des Sections 3.5.2, 3.5.4 et 3.5.6 doit être égale ou supérieure au "Total" en "Ni confirmée ni infirmée" de la Section 3.1 | AA86: =SUM(AA135,AC152,AD169)
A87: Total | D87: =SUM(D80:D86) | E87: =SUM(E80:E86) | F87: =SUM(F80:F86) | G87: =SUM(G80:G86) | H87: =SUM(H80:H86) | I87: =SUM(I80:I86) | J87: =SUM(J80:J86) | K87: =SUM(K80:K86) | L87: Section 3.1 - La somme des totaux de la Rangée 8 doit être égale au montant de "Fermées pendant la période d'établissement de rapport" de la Section 1.1 | AA87: =SUM(AA136,AC153,AD170)
K88: =SUM(K80:K83,K85:K86)
A90: 3.2 Exceptions
A92: Article | C92: Nombre de demandes | E92: Article | G92: Nombre de demandes | I92: Article | K92: Nombre de demandes
A93: 18(2) | C93: 0 | E93: 22(1)a)(i) | G93: 0 | I93: 23a) | K93: 0
A94: 19(1)a) | C94: 0 | E94: 22(1)a)(ii) | G94: 0 | I94: 23b) | K94: 0
A95: 19(1)b) | C95: 0 | E95: 22(1)a)(iii) | G95: 0 | I95: 24a) | K95: 0
A96: 19(1)c) | C96: 0 | E96: 22(1)b) | G96: 0 | I96: 24b) | K96: 0
A97: 19(1)d) | C97: 0 | E97: 22(1)c) | G97: 0 | I97: 25 | K97: 0
A98: 19(1)e) | C98: 0 | E98: 22(2) | G98: 0 | I98: 26 | K98: 0
A99: 19(1)f) | C99: 0 | E99: 22.1 | G99: 0 | I99: 27 | K99: 0
A100: 20 | C100: 0 | E100: 22.2 | G100: 0 | I100: 27.1 | K100: 0
A101: 21 | C101: 0 | E101: 22.3 | G101: 0 | I101: 28 | K101: 0 | M101: =IF(AND(SUM(C93:D101,G93:H102,K93:L101)>0,SUM(K81,K82,K85)=0),"Si le nombre total de demandes indiqué au tableau 3.2 est supérieur à zéro, le nombre total de demandes indiqué aux rangées 2, 3 et 6 de la colonne 8 du tableau 3.1 doit être supérieur à zéro.","")
E102: 22.4 | G102: 0
A104: 3.3 Exclusions
A106: Article | C106: Nombre de demandes | E106: Article | G106: Nombre de demandes | I106: Article | K106: Nombre de demandes
A107: 69(1)a) | C107: 0 | E107: 70(1) | G107: 0 | I107: 70(1)d) | K107: 0
A108: 69(1)b) | C108: 0 | E108: 70(1)a) | G108: 0 | I108: 70(1)e) | K108: 0
A109: 69.1 | C109: 0 | E109: 70(1)b) | G109: 0 | I109: 70(1)f) | K109: 0
E110: 70(1)c) | G110: 0 | I110: 70.1 | K110: 0 | M110: =IF(AND(SUM(C107:D109,G107:H110,K107:L110)>0,SUM(K81,K83,K85)=0),"Si le nombre total de demandes indiqué au tableau 3.3 est supérieur à zéro, le nombre total de demandes indiqué dans les rangées 2, 4 et 6 de la colonne 8 du tableau 3.1 doit être supérieur à zéro.","")
M111: =IF(SUM(A116:I116)<SUM(K80,K81),"Section 3.4 - Le montant total de ""Papier, Électronique et Autres"" doit être égal ou supérieur au ""Total"" de ""Communication totale"" et ""Communication partielle"" de Section 3.1","")
A112: 3.4 Format des documents communiqués
M113: =IF(A116>SUM(K80:K81),"Section 3.4 - Le montant total de ""Papier"" de ""Format des documents communiqués"" doit être égal ou inférieur au ""Total"" de ""Communication totale"" et ""Communication partielle"" de Section 3.1","")
A114: Papier | C114: Électronique | H114: Autres | M114: =IF(C116>SUM(K80,K81),"Section 3.4 - Le montant total de ""Document électronique"" de ""Format des documents communiqués"" doit être égal ou inférieur au ""Total"" de ""Communication totale"" et ""Communication partielle"" de Section 3.1","")
C115: Document électronique | E115: Ensemble de données | F115: Vidéo | G115: Audio | M115: =IF(E116>SUM(K80,K81),"Section 3.4 - Le montant total de ""Ensemble de données"" de ""Format des documents communiqués"" doit être égal ou inférieur au ""Total"" de ""Communication totale"" et ""Communication partielle"" de Section 3.1","")
A116: 0 | C116: 0 | E116: 0 | F116: 0 | G116: 0 | H116: 0 | M116: =IF(F116>SUM(K80,K81),"Section 3.4 - Le montant total de ""Vidéo"" de ""Format des documents communiqués"" doit être égal ou inférieur au ""Total"" de ""Communication totale"" et ""Communication partielle"" de Section 3.1","")
M117: =IF(G116>SUM(K80,K81),"Section 3.4 - Le montant total de ""Audio"" de ""Format des documents communiqués"" doit être égal ou inférieur au ""Total"" de ""Communication totale"" et ""Communication partielle"" de Section 3.1","")
A118: 3.5 Complexité | M118: =IF(H116>SUM(K80,K81),"Section 3.4 - Le montant total de ""Autres"" de ""Format des documents communiqués"" doit être égal ou inférieur au ""Total"" de ""Communication totale"" et ""Communication partielle"" de Section 3.1","")
M119: =IF(SUM(A116,C116,E116,H116)<= G123,"","Le nombre total de demandes en formats ""Papier"", ""Document électronique"", ""Ensemble de données"" et ""Autres"" du tableau 3.4 doit être égal ou inférieur au nombre total de demandes indiqué dans ""Nombre de demandes"" du tableau 3.5.1.")
A120: 3.5.1 Pages pertinentes traitées et communiquées en formats papier, document électronique et ensemble de données | M120: =IF(F116<=G158,"","Le nombre total de demandes de documents ""Vidéo"" indiqué dans le tableau 3.4 doit être égal ou inférieur au ""Nombre de demandes"" indiqué dans le tableau 3.5.5.")
M121: =IF(G116<=G141,"","Le nombre total de demandes de documents ""Audio"" indiqué dans le tableau 3.4 doit être égal ou inférieur au ""Nombre de demandes"" indiqué dans le tableau 3.5.3.")
A122: Nombre de pages traitées | D122: Nombre de pages communiquées | G122: Nombre de demandes | J122: Section 3.5.1 - Le "Nombre de pages communiquées" doit être égal ou inférieur au "Nombre de pages traitées".
A123: 0 | D123: 0 | G123: 0 | J123: Section 3.5.1 - Le "Nombre de demandes" doit être égal ou inférieur à la somme des demandes en dispositions "Communication totale", "Communication partielle", "Exception totale", "Exclusion totale", "Demande abandonnée" et "Ni confirmée ni infirmée" de la Section 3.1
A125: 3.5.2 Pages pertinentes traitées en fonction de l’ampleur des demandes en formats papier, document électronique et ensemble de données par disposition des demandes | M125: =IFERROR(IF(D136/C136>99,"Section 3.5.2 - Le nombre total de pages ""Pages traitées"" divisé par le ""Nombre de demandes"" dans ""Moins de 100 pages traitées"" doit être égal ou inférieur à 99.",""),"")
...

Sheet ATI_ForConsumption
A1: Inst | B1: =LAI!D6
A2: Report | B2: 2021;2022
A3: Q1R1C1 | B3: =LAI!H14 | C3: 1,1
A4: Q1R2C1 | B4: =LAI!H15 | C4: 1,1
A5: Q1R3C1 | B5: =LAI!G16 | C5: 1,1
A6: Q1R4C1 | B6: =LAI!G17 | C6: 1,1
A7: Q1R5C1 | B7: =LAI!H18 | C7: 1,1
A8: Q1R6C1 | B8: =LAI!H19 | C8: 1,1
A9: Q1R7C1 | B9: =LAI!H20 | C9: 1,1
A10: Q1R8C1 | B10: =LAI!G21 | C10: 1,1
A11: Q1R9C1 | B11: =LAI!G22 | C11: 1,1
A12: Q2R1C1 | B12: =LAI!G27 | C12: 1,2
A13: Q2R2C1 | B13: =LAI!G28 | C13: 1,2
A14: Q2R3C1 | B14: =LAI!G29 | C14: 1,2
A15: Q2R4C1 | B15: =LAI!G30 | C15: 1,2
A16: Q2R5C1 | B16: =LAI!G31 | C16: 1,2
A17: Q2R6C1 | B17: =LAI!G32 | C17: 1,2
A18: Q2R7C1 | B18: =LAI!G33 | C18: 1,2
A19: Q3R1C1 | B19: =LAI!G38 | C19: 1,3
A20: Q3R2C1 | B20: =LAI!G39 | C20: 1,3
A21: Q3R3C1 | B21: =LAI!G40 | C21: 1,3
A22: Q3R4C1 | B22: =LAI!G41 | C22: 1,3
A23: Q3R5C1 | B23: =LAI!G42 | C23: 1,3
A24: Q3R6C1 | B24: =LAI!G43 | C24: 1,3
A25: Q3R7C1 | B25: =LAI!G44 | C25: 1,3
A26: Q4R1C1 | B26: =LAI!H50 | C26: 2,1
A27: Q4R2C1 | B27: =LAI!H51 | C27: 2,1
A28: Q4R3C1 | B28: =LAI!G52 | C28: 2,1
A29: Q4R4C1 | B29: =LAI!G53 | C29: 2,1
A30: Q4R5C1 | B30: =LAI!H54 | C30: 2,1
A31: Q4R6C1 | B31: =LAI!H55 | C31: 2,1
A32: Q4R7C1 | B32: =LAI!H56 | C32: 2,1
A33: Q5R1C1 | B33: =LAI!G61 | C33: 2,2
A34: Q5R2C1 | B34: =LAI!G62 | C34: 2,2
A35: Q5R3C1 | B35: =LAI!G63 | C35: 2,2
A36: Q5R4C1 | B36: =LAI!G64 | C36: 2,2
A37: Q5R5C1 | B37: =LAI!G65 | C37: 2,2
A38: Q5R6C1 | B38: =LAI!G66 | C38: 2,2
A39: Q5R7C1 | B39: =LAI!G67 | C39: 2,2
A40: Q6R1C1 | B40: =LAI!A73 | C40: 2,3
A41: Q6R1C2 | B41: =LAI!B73 | C41: 2,3
A42: Q6R1C3 | B42: =LAI!C73 | C42: 2,3
A43: Q6R1C4 | B43: =LAI!D73 | C43: 2,3
A44: Q6R1C5 | B44: =LAI!E73 | C44: 2,3
A45: Q6R1C6 | B45: =LAI!F73 | C45: 2,3
A46: Q6R1C7 | B46: =LAI!G73 | C46: 2,3
A47: Q7R1C1 | B47: =LAI!A79 | C47: 2,4
A48: Q7R1C2 | B48: =LAI!B79 | C48: 2,4
A49: Q7R1C3 | B49: =LAI!C79 | C49: 2,4
A50: Q7R1C4 | B50: =LAI!D79 | C50: 2,4
A51: Q7R1C5 | B51: =LAI!E79 | C51: 2,4
A52: Q7R1C6 | B52: =LAI!F79 | C52: 2,4
A53: Q7R1C7 | B53: =LAI!G79 | C53: 2,4
A54: Q7R1C8 | B54: =LAI!H79 | C54: 2,4
A55: Q7R1C9 | B55: =LAI!I79 | C55: 2,4
A56: Q7R1C10 | B56: =LAI!J79 | C56: 2,4
A57: Q8R1C1 | B57: =LAI!A85 | C57: 2,5
A58: Q8R1C2 | B58: =LAI!B85 | C58: 2,5
A59: Q8R1C3 | B59: =LAI!C85 | C59: 2,5
A60: Q8R1C4 | B60: =LAI!D85 | C60: 2,5
A61: Q8R1C5 | B61: =LAI!E85 | C61: 2,5
A62: Q8R1C6 | B62: =LAI!F85 | C62: 2,5
A63: Q8R1C7 | B63: =LAI!G85 | C63: 2,5
A64: Q8R1C8 | B64: =LAI!H85 | C64: 2,5
A65: Q8R1C9 | B65: =LAI!I85 | C65: 2,5
A66: Q8R1C10 | B66: =LAI!J85 | C66: 2,5
A67: Q9R1C1 | B67: =LAI!H90 | C67: 3
A68: Q9R2C1 | B68: =LAI!H91 | C68: 3
A69: Q9R3C1 | B69: =LAI!H92 | C69: 3
A70: Q9R4C1 | B70: =LAI!H93 | C70: 3
A71: Q9R5C1 | B71: =LAI!H94 | C71: 3
A72: Q9R6C1 | B72: =LAI!H95 | C72: 3
A73: Q9R7C1 | B73: =LAI!H96 | C73: 3
A74: Q10R1C1 | B74: =LAI!E104 | C74: 4,1
A75: Q10R1C2 | B75: =LAI!F104 | C75: 4,1
A76: Q10R1C3 | B76: =LAI!G104 | C76: 4,1
A77: Q10R1C4 | B77: =LAI!H104 | C77: 4,1
A78: Q10R1C5 | B78: =LAI!I104 | C78: 4,1
A79: Q10R1C6 | B79: =LAI!J104 | C79: 4,1
A80: Q10R1C7 | B80: =LAI!K104 | C80: 4,1
A81: Q10R2C1 | B81: =LAI!E105 | C81: 4,1
A82: Q10R2C2 | B82: =LAI!F105 | C82: 4,1
A83: Q10R2C3 | B83: =LAI!G105 | C83: 4,1
A84: Q10R2C4 | B84: =LAI!H105 | C84: 4,1
A85: Q10R2C5 | B85: =LAI!I105 | C85: 4,1
A86: Q10R2C6 | B86: =LAI!J105 | C86: 4,1
A87: Q10R2C7 | B87: =LAI!K105 | C87: 4,1
A88: Q10R3C1 | B88: =LAI!E106 | C88: 4,1
A89: Q10R3C2 | B89: =LAI!F106 | C89: 4,1
A90: Q10R3C3 | B90: =LAI!G106 | C90: 4,1
A91: Q10R3C4 | B91: =LAI!H106 | C91: 4,1
A92: Q10R3C5 | B92: =LAI!I106 | C92: 4,1
A93: Q10R3C6 | B93: =LAI!J106 | C93: 4,1
A94: Q10R3C7 | B94: =LAI!K106 | C94: 4,1
A95: Q10R4C1 | B95: =LAI!E107 | C95: 4,1
A96: Q10R4C2 | B96: =LAI!F107 | C96: 4,1
A97: Q10R4C3 | B97: =LAI!G107 | C97: 4,1
A98: Q10R4C4 | B98: =LAI!H107 | C98: 4,1
A99: Q10R4C5 | B99: =LAI!I107 | C99: 4,1
A100: Q10R4C6 | B100: =LAI!J107 | C100: 4,1
...

Sheet Privacy_ForConsumption
A1: Inst | B1: =LPRP!H6
A2: Report | B2: 2021;2022
A3: Q1R1C1 | B3: =LPRP!H15 | C3: 1,1
A4: Q1R2C1 | B4: =LPRP!H16 | C4: 1,1
A5: Q1R3C1 | B5: =LPRP!G17 | C5: 1,1
A6: Q1R4C1 | B6: =LPRP!G18 | C6: 1,1
A7: Q1R5C1 | B7: =LPRP!H19 | C7: 1,1
A8: Q1R6C1 | B8: =LPRP!H20 | C8: 1,1
A9: Q1R7C1 | B9: =LPRP!H21 | C9: 1,1
A10: Q1R8C1 | B10: =LPRP!G22 | C10: 1,1
A11: Q1R9C1 | B11: =LPRP!G23 | C11: 1,1
A12: Q2R1C1 | B12: =LPRP!G28 | C12: 1,2
A13: Q2R2C1 | B13: =LPRP!G29 | C13: 1,2
A14: Q2R3C1 | B14: =LPRP!G30 | C14: 1,2
A15: Q2R4C1 | B15: =LPRP!G31 | C15: 1,2
A16: Q2R5C1 | B16: =LPRP!G32 | C16: 1,2
A17: Q2R6C1 | B17: =LPRP!G33 | C17: 1,2
A18: Q2R7C1 | B18: =LPRP!G34 | C18: 1,2
A19: Q3R1C1 | B19: =LPRP!H42 | C19: 2,1
A20: Q3R2C1 | B20: =LPRP!H43 | C20: 2,1
A21: Q3R3C1 | B21: =LPRP!G44 | C21: 2,1
A22: Q3R4C1 | B22: =LPRP!G45 | C22: 2,1
A23: Q3R5C1 | B23: =LPRP!H46 | C23: 2,1
A24: Q3R6C1 | B24: =LPRP!H47 | C24: 2,1
A25: Q3R7C1 | B25: =LPRP!H48 | C25: 2,1
A26: Q4R1C1 | B26: =LPRP!G53 | C26: 2,2
A27: Q4R2C1 | B27: =LPRP!G54 | C27: 2,2
A28: Q4R3C1 | B28: =LPRP!G55 | C28: 2,2
A29: Q4R4C1 | B29: =LPRP!G56 | C29: 2,2
A30: Q4R5C1 | B30: =LPRP!G57 | C30: 2,2
A31: Q4R6C1 | B31: =LPRP!G58 | C31: 2,2
A32: Q4R7C1 | B32: =LPRP!G59 | C32: 2,2
A33: Q5R1C1 | B33: =LPRP!A65 | C33: 2,3
A34: Q5R1C2 | B34: =LPRP!B65 | C34: 2,3
A35: Q5R1C3 | B35: =LPRP!C65 | C35: 2,3
A36: Q5R1C4 | B36: =LPRP!D65 | C36: 2,3
A37: Q5R1C5 | B37: =LPRP!E65 | C37: 2,3
A38: Q5R1C6 | B38: =LPRP!F65 | C38: 2,3
A39: Q5R1C7 | B39: =LPRP!G65 | C39: 2,3
A40: Q6R1C1 | B40: =LPRP!A71 | C40: 2,4
A41: Q6R1C2 | B41: =LPRP!B71 | C41: 2,4
A42: Q6R1C3 | B42: =LPRP!C71 | C42: 2,4
A43: Q6R1C4 | B43: =LPRP!D71 | C43: 2,4
A44: Q6R1C5 | B44: =LPRP!E71 | C44: 2,4
A45: Q6R1C6 | B45: =LPRP!F71 | C45: 2,4
A46: Q6R1C7 | B46: =LPRP!G71 | C46: 2,4
A47: Q6R1C8 | B47: =LPRP!H71 | C47: 2,4
A48: Q6R1C9 | B48: =LPRP!I71 | C48: 2,4
A49: Q6R1C10 | B49: =LPRP!J71 | C49: 2,4
A50: Q7R1C1 | B50: =LPRP!D80 | C50: 3,1
A51: Q7R1C2 | B51: =LPRP!E80 | C51: 3,1
A52: Q7R1C3 | B52: =LPRP!F80 | C52: 3,1
A53: Q7R1C4 | B53: =LPRP!G80 | C53: 3,1
A54: Q7R1C5 | B54: =LPRP!H80 | C54: 3,1
A55: Q7R1C6 | B55: =LPRP!I80 | C55: 3,1
A56: Q7R1C7 | B56: =LPRP!J80 | C56: 3,1
A57: Q7R2C1 | B57: =LPRP!D81 | C57: 3,1
A58: Q7R2C2 | B58: =LPRP!E81 | C58: 3,1
A59: Q7R2C3 | B59: =LPRP!F81 | C59: 3,1
A60: Q7R2C4 | B60: =LPRP!G81 | C60: 3,1
A61: Q7R2C5 | B61: =LPRP!H81 | C61: 3,1
A62: Q7R2C6 | B62: =LPRP!I81 | C62: 3,1
A63: Q7R3C7 | B63: =LPRP!J81 | C63: 3,1
A64: Q7R3C1 | B64: =LPRP!D82 | C64: 3,1
A65: Q7R3C2 | B65: =LPRP!E82 | C65: 3,1
A66: Q7R3C3 | B66: =LPRP!F82 | C66: 3,1
A67: Q7R3C4 | B67: =LPRP!G82 | C67: 3,1
A68: Q7R3C5 | B68: =LPRP!H82 | C68: 3,1
A69: Q7R3C6 | B69: =LPRP!I82 | C69: 3,1
A70: Q7R3C7 | B70: =LPRP!J82 | C70: 3,1
A71: Q7R4C1 | B71: =LPRP!D83 | C71: 3,1
A72: Q7R4C2 | B72: =LPRP!E83 | C72: 3,1
A73: Q7R4C3 | B73: =LPRP!F83 | C73: 3,1
A74: Q7R4C4 | B74: =LPRP!G83 | C74: 3,1
A75: Q7R4C5 | B75: =LPRP!H83 | C75: 3,1
A76: Q7R4C6 | B76: =LPRP!I83 | C76: 3,1
A77: Q7R4C7 | B77: =LPRP!J83 | C77: 3,1
A78: Q7R5C1 | B78: =LPRP!D84 | C78: 3,1
A79: Q7R5C2 | B79: =LPRP!E84 | C79: 3,1
A80: Q7R5C3 | B80: =LPRP!F84 | C80: 3,1
A81: Q7R5C4 | B81: =LPRP!G84 | C81: 3,1
A82: Q7R5C5 | B82: =LPRP!H84 | C82: 3,1
A83: Q7R5C6 | B83: =LPRP!I84 | C83: 3,1
A84: Q7R5C7 | B84: =LPRP!J84 | C84: 3,1
A85: Q7R6C1 | B85: =LPRP!D85 | C85: 3,1
A86: Q7R6C2 | B86: =LPRP!E85 | C86: 3,1
A87: Q7R6C3 | B87: =LPRP!F85 | C87: 3,1
A88: Q7R6C4 | B88: =LPRP!G85 | C88: 3,1
A89: Q7R6C5 | B89: =LPRP!H85 | C89: 3,1
A90: Q7R6C6 | B90: =LPRP!I85 | C90: 3,1
A91: Q7R6C7 | B91: =LPRP!J85 | C91: 3,1
A92: Q7R7C1 | B92: =LPRP!D86 | C92: 3,1
A93: Q7R7C2 | B93: =LPRP!E86 | C93: 3,1
A94: Q7R7C3 | B94: =LPRP!F86 | C94: 3,1
A95: Q7R7C4 | B95: =LPRP!G86 | C95: 3,1
A96: Q7R7C5 | B96: =LPRP!H86 | C96: 3,1
A97: Q7R7C6 | B97: =LPRP!I86 | C97: 3,1
A98: Q7R7C7 | B98: =LPRP!J86 | C98: 3,1
A99: Q8R1C1 | B99: =LPRP!C93 | C99: 3,2
A100: Q8R2C1 | B100: =LPRP!C94 | C100: 3,2
...
